odoo10_addon_partner_contact_nationality-10.0.1.0.0-py2.7-nspkg.pth
odoo/addons/partner_contact_nationality/README.rst
odoo/addons/partner_contact_nationality/__init__.py
odoo/addons/partner_contact_nationality/__manifest__.py
odoo/addons/partner_contact_nationality/i18n/da.po
odoo/addons/partner_contact_nationality/i18n/de.po
odoo/addons/partner_contact_nationality/i18n/es.po
odoo/addons/partner_contact_nationality/i18n/fr.po
odoo/addons/partner_contact_nationality/i18n/hr_HR.po
odoo/addons/partner_contact_nationality/i18n/it.po
odoo/addons/partner_contact_nationality/i18n/nl.po
odoo/addons/partner_contact_nationality/i18n/partner_contact_nationality.pot
odoo/addons/partner_contact_nationality/i18n/pt_BR.po
odoo/addons/partner_contact_nationality/i18n/sl.po
odoo/addons/partner_contact_nationality/models/__init__.py
odoo/addons/partner_contact_nationality/models/res_partner.py
odoo/addons/partner_contact_nationality/static/description/icon.png
odoo/addons/partner_contact_nationality/views/res_partner.xml
odoo10_addon_partner_contact_nationality-10.0.1.0.0.dist-info/DESCRIPTION.rst
odoo10_addon_partner_contact_nationality-10.0.1.0.0.dist-info/METADATA
odoo10_addon_partner_contact_nationality-10.0.1.0.0.dist-info/RECORD
odoo10_addon_partner_contact_nationality-10.0.1.0.0.dist-info/WHEEL
odoo10_addon_partner_contact_nationality-10.0.1.0.0.dist-info/metadata.json
odoo10_addon_partner_contact_nationality-10.0.1.0.0.dist-info/namespace_packages.txt
odoo10_addon_partner_contact_nationality-10.0.1.0.0.dist-info/top_level.txt
