Metadata-Version: 2.0
Name: odoo10-addon-partner-contact-nationality
Version: 10.0.1.0.0
Summary: Add nationality field to contacts
Home-page: https://odoo-community.org/
Author: Grupo ESOC, Odoo Community Association (OCA)
Author-email: support@odoo-community.org
License: AGPL-3
Platform: UNKNOWN
Classifier: Programming Language :: Python :: 2.7
Classifier: Framework :: Odoo
Classifier: License :: OSI Approved :: GNU Affero General Public License v3
Requires-Dist: odoo (<10.1dev,>=10.0)
Requires-Dist: odoo10-addon-partner-contact-personal-information-page
